msa_exam/__init__.py
msa_exam/unit1.py
msa_exam/unit2_1.py
msa_exam/unit2_2.py
msa_exam/unit2_3.py
msa_exam/unit2_4.py
msa_exam/unit2_5.py
msa_exam/unit2_6.py
msa_exam/unit3.py
msa_exam/unit4.py
msa_exam/unit5.py
msa_exam-0.0.1.dist-info/LICENSE
msa_exam-0.0.1.dist-info/METADATA
msa_exam-0.0.1.dist-info/WHEEL
msa_exam-0.0.1.dist-info/top_level.txt
msa_exam-0.0.1.dist-info/RECORD
